<?xml version='1.0' encoding='UTF-8'?>
<SubTopic id="19657466" name="足球迷"><q i="1" t="2016-12-19"><v>1620</v><t>和职业球员一起踢球是种怎么样的体验？</t></q><q i="2" t="2016-07-30"><v>1173</v><t>有哪些足球照片一张就是一个故事 ？</t></q><q i="3" t="2012-11-07"><v>1053</v><t>足球中，让你感觉最悲情的场景是哪个？</t></q><q i="4" t="2014-06-29"><v>970</v><t>如何评价智利国家队？</t></q><q i="5" t="2016-03-05"><v>847</v><t>有哪些足球照片一张就是一个故事 ？</t></q><q i="6" t="2012-11-05"><v>535</v><t>足球中，让你感觉最悲情的场景是哪个？</t></q><q i="7" t="2015-11-11"><v>457</v><t>如何评价刚刚官方公布的广州恒大 2015 年亚冠决赛的球票价格？</t></q><q i="8" t="2013-07-10"><v>336</v><t>和职业球员一起踢球是种怎么样的体验？</t></q><q i="9" t="2015-06-04"><v>271</v><t>罗伊斯26岁什么荣誉都没有，为什么还有人喜欢他？</t></q><q i="10" t="2014-09-14"><v>210</v><t>哪位足球运动员靠演技度过足球生涯，从未踢过球，每次都装病不上场？</t></q><q i="11" t="2016-12-07"><v>203</v><t>有没有足球女教练？</t></q><q i="12" t="2014-05-31"><v>183</v><t>德国家庭对于孩子踢足球的态度是怎样的？是什么原因使得德国成为每百万人注册球员数量全球第一的？</t></q><q i="13" t="2014-12-31"><v>172</v><t>当巴萨球迷是什么体验？</t></q><q i="14" t="2016-05-11"><v>171</v><t>为了国家荣誉，可以把所有国家队球员放进一个俱乐部吗？</t></q><q i="15" t="2014-07-15"><v>164</v><t>伪球迷如何晋升为球迷？</t></q><q i="16" t="2014-12-31"><v>159</v><t>当巴萨球迷是什么体验？</t></q><q i="17" t="2015-08-08"><v>156</v><t>如何给阿森纳俱乐部写信？</t></q><q i="18" t="2014-04-30"><v>153</v><t>男朋友是拜仁球迷，输球了怎么安慰他？</t></q><q i="19" t="2015-10-21"><v>149</v><t>如何让妹子入门足球球迷？</t></q><q i="20" t="2013-03-08"><v>141</v><t>既踢球又看球的人与只看不踢的人，在对足球的理解上有何不同？</t></q><q i="21" t="2014-06-20"><v>136</v><t>意大利正版球衣在哪里可以买到？</t></q><q i="22" t="2015-04-17"><v>117</v><t>请用图文并茂简单粗暴的办法让一位小白妹子看懂球赛？</t></q><q i="23" t="2014-05-01"><v>106</v><t>如何看待鲁能目前所处的境况？</t></q><q i="24" t="2015-11-12"><v>103</v><t>如何评价刚刚官方公布的广州恒大 2015 年亚冠决赛的球票价格？</t></q><q i="25" t="2013-07-16"><v>97</v><t>为什么国内的野球水平会令人恐怖的低呢？</t></q><q i="26" t="2014-09-12"><v>86</v><t>为什么很多人都说高估了鲁尼的能力？真的是这样吗？</t></q><q i="27" t="2015-06-05"><v>84</v><t>罗伊斯26岁什么荣誉都没有，为什么还有人喜欢他？</t></q><q i="28" t="2014-07-10"><v>76</v><t>德国家庭对于孩子踢足球的态度是怎样的？是什么原因使得德国成为每百万人注册球员数量全球第一的？</t></q><q i="29" t="2014-05-04"><v>75</v><t>如何看待鲁能目前所处的境况？</t></q><q i="30" t="2014-03-16"><v>75</v><t>football manager是如何做到如此精细的数据收集的？</t></q><q i="31" t="2013-07-08"><v>71</v><t>天赋高的球员大多是进攻型，这个说法有道理吗？</t></q><q i="32" t="2014-01-27"><v>66</v><t>送什么礼物给喜欢足球的女生呢？</t></q><q i="33" t="2013-01-15"><v>64</v><t>《天下足球》和《足球之夜》有何异同？</t></q><q i="34" t="2015-06-12"><v>74</v><t>罗伊斯26岁什么荣誉都没有，为什么还有人喜欢他？</t></q><q i="35" t="2015-04-15"><v>63</v><t>如何给阿森纳俱乐部写信？</t></q><q i="36" t="2015-11-12"><v>61</v><t>零基础如何学习fm2015?</t></q><q i="37" t="2015-06-04"><v>58</v><t>欧冠决赛 ，巴塞罗那和尤文图斯你更看好谁夺冠？理由？</t></q><q i="38" t="2016-03-02"><v>57</v><t>既踢球又看球的人与只看不踢的人，在对足球的理解上有何不同？</t></q><q i="39" t="2014-06-30"><v>57</v><t>“无冕之王”荷兰队现在的实力对比2010年时是进步了还是退步了？</t></q><q i="40" t="2014-02-08"><v>56</v><t>如何评价詹俊？</t></q><q i="41" t="2015-05-09"><v>56</v><t>足球和建筑有什么关系？</t></q><q i="42" t="2014-01-09"><v>55</v><t>足球界有哪些有意思的短笑话？</t></q><q i="43" t="2016-12-22"><v>54</v><t>杰拉德位置后移效果如何？</t></q><q i="44" t="2015-11-11"><v>53</v><t>如何评价詹俊？</t></q><q i="45" t="2015-11-18"><v>53</v><t>世界上最伟大的守门员是谁？</t></q><q i="46" t="2012-10-15"><v>52</v><t>怎么评价坎通纳？</t></q><q i="47" t="2013-09-16"><v>52</v><t>为什么荷甲成不了世界最一流联赛？</t></q><q i="48" t="2016-07-27"><v>52</v><t>如何让妹子入门足球球迷？</t></q><q i="49" t="2014-02-16"><v>51</v><t>弗格森留给莫耶斯的是个烂摊子吗？</t></q><q i="50" t="2013-12-10"><v>51</v><t>如何从观看足球比赛中获得乐趣？</t></q><q i="51" t="2013-08-20"><v>49</v><t>请客观综合地评价下莫德里奇？</t></q><q i="52" t="2014-12-29"><v>49</v><t>我真的想踢好球，怎么提高?</t></q><q i="53" t="2014-04-25"><v>49</v><t>足球球衣的类别?</t></q><q i="54" t="2014-01-08"><v>45</v><t>足球界有哪些有意思的短笑话？</t></q><q i="55" t="2014-07-02"><v>43</v><t>如何评价智利国家队？</t></q><q i="56" t="2014-03-25"><v>43</v><t>为什么女生难懂足球？</t></q><q i="57" t="2014-03-31"><v>42</v><t>女生如何练习足球？</t></q><q i="58" t="2016-12-11"><v>42</v><t>在FM的游戏过程中，你遇见过什么搞笑的情况？</t></q><q i="59" t="2014-04-29"><v>41</v><t>梅西能离开巴萨吗？</t></q><q i="60" t="2013-10-03"><v>40</v><t>是什么原因支持着保级水平球队的球迷依然坚守？</t></q><q i="61" t="2014-01-03"><v>40</v><t>西班牙队几名首发位置不稳固的中场球员席尔瓦、马塔、卡索拉的风格有什么不同？</t></q><q i="62" t="2016-01-09"><v>39</v><t>一个人如何进行系统的足球训练?</t></q><q i="63" t="2016-04-11"><v>38</v><t>本田圭佑和香川真司相较如何?</t></q><q i="64" t="2015-02-21"><v>38</v><t>为什么很多连球迷都觉得错误的决策，一再地被专业的经理做出来？</t></q><q i="65" t="2014-02-13"><v>38</v><t>谁是你见过的最优雅的球星?</t></q><q i="66" t="2013-08-09"><v>37</v><t>如何短期足球入门？</t></q><q i="67" t="2015-05-07"><v>37</v><t>足球和建筑有什么关系？</t></q><q i="68" t="2014-05-06"><v>37</v><t>怎么评价坎通纳？</t></q><q i="69" t="2015-06-03"><v>37</v><t>为什么布拉特可以担任国际足联主席这么久？</t></q><q i="70" t="2013-09-22"><v>36</v><t>为什么足球门将接回传球时，必须先脚触下，才能用手接？</t></q><q i="71" t="2014-02-24"><v>37</v><t>为什么足协一直不选择特鲁西埃执教中国？</t></q><q i="72" t="2013-08-09"><v>34</v><t>如何短期足球入门？</t></q><q i="73" t="2013-07-28"><v>34</v><t>突然发现2014要来了怎么迅速懂足球啊？</t></q><q i="74" t="2015-05-31"><v>34</v><t>如果中国队申办世界杯成功，会不会出现大量中国球迷穿外国球衣观看比赛的情况？</t></q><q i="75" t="2015-11-02"><v>33</v><t>为什么感觉只有米兰球迷一直在怀念过去？</t></q><q i="76" t="2015-03-12"><v>33</v><t>完全不懂足球如何在 2014 年世界杯期间装作懂球？</t></q><q i="77" t="2014-02-13"><v>33</v><t>谁是你见过的最优雅的球星?</t></q><q i="78" t="2014-09-08"><v>32</v><t>为什么很多人都说高估了鲁尼的能力？真的是这样吗？</t></q><q i="79" t="2014-04-12"><v>32</v><t>求助！我想给ac米兰写封信。他们会回复吗?</t></q><q i="80" t="2014-03-07"><v>32</v><t>妹子是球迷而我不是的情况下，第一次陪妹子到现场看球应该了解什么？怎么做才不会冷场？</t></q><q i="81" t="2014-02-23"><v>31</v><t>如何评价「球迷」？</t></q><q i="82" t="2014-06-27"><v>30</v><t>巴西世界杯亚洲球队集体出局是真实水平的反映吗？</t></q><q i="83" t="2015-07-16"><v>30</v><t>怎么伪装成国米球迷?</t></q><q i="84" t="2014-03-12"><v>30</v><t>一只球队的教练和核心队员都变了，支持你继续支持它的又是什么?</t></q><q i="85" t="2014-03-07"><v>29</v><t>妹子是球迷而我不是的情况下，第一次陪妹子到现场看球应该了解什么？怎么做才不会冷场？</t></q><q i="86" t="2014-12-26"><v>28</v><t>如何听懂德语足球解说？</t></q><q i="87" t="2015-09-11"><v>27</v><t>如何评价托蒂，算是现象级球星吗？</t></q><q i="88" t="2013-07-16"><v>26</v><t>为什么国内的野球水平会令人恐怖的低呢？</t></q><q i="89" t="2015-11-08"><v>26</v><t>为什么感觉只有米兰球迷一直在怀念过去？</t></q><q i="90" t="2015-08-31"><v>26</v><t>德布劳内凭什么值8000万欧元？</t></q><q i="91" t="2015-06-11"><v>26</v><t>欧冠决赛 ，巴塞罗那和尤文图斯你更看好谁夺冠？理由？</t></q><q i="92" t="2014-04-20"><v>26</v><t>为什么沃尔科特不像贝尔一样强行超车？</t></q><q i="93" t="2014-02-16"><v>26</v><t>为什么足球运动员喜欢在被打到其他部位时捂着脸倒地？</t></q><q i="94" t="2013-01-17"><v>25</v><t>《天下足球》和《足球之夜》有何异同？</t></q><q i="95" t="2015-02-21"><v>25</v><t>为什么很多连球迷都觉得错误的决策，一再地被专业的经理做出来？</t></q><q i="96" t="2015-01-08"><v>25</v><t>我真的想踢好球，怎么提高?</t></q><q i="97" t="2012-04-09"><v>25</v><t>足球迷们为自己的喜欢的球队相互攻击对骂，这可以说是一种“足球文化”？</t></q><q i="98" t="2014-04-18"><v>25</v><t>如何评价多特蒙德的罗伊斯？</t></q><q i="99" t="2013-11-30"><v>23</v><t>恒大的管理模式和巴黎圣日耳曼的管理模式有什么异同？</t></q><q i="100" t="2015-05-20"><v>22</v><t>2015年欧冠半决赛皇马VS尤文，为何各大门户网站都认为是贝尔的错？</t></q><q i="101" t="2014-10-03"><v>22</v><t>怎么评价pptv周亮在解说时公然称江苏舜天球员为苏北狗？</t></q><q i="102" t="2015-02-03"><v>21</v><t>如果要世界顶级门将守门，让业余玩球的人去踢点球，10个能进几个？</t></q><q i="103" t="2014-06-30"><v>25</v><t>巴西下一轮有可能战胜哥伦比亚吗？</t></q><q i="104" t="2014-02-17"><v>21</v><t>弗格森留给莫耶斯的是个烂摊子吗？</t></q><q i="105" t="2015-12-11"><v>20</v><t>自己主队有一个世界级门将是什么体验？</t></q><q i="106" t="2014-10-21"><v>20</v><t>为了国家荣誉，可以把所有国家队球员放进一个俱乐部吗？</t></q><q i="107" t="2014-06-18"><v>20</v><t>足球比赛中观众如何发起一次人浪？</t></q><q i="108" t="2014-06-15"><v>20</v><t>足球比赛中有哪些很无语的规则？</t></q><q i="109" t="2015-03-10"><v>19</v><t>请客观综合地评价下莫德里奇？</t></q><q i="110" t="2015-06-03"><v>19</v><t>欧冠决赛 ，巴塞罗那和尤文图斯你更看好谁夺冠？理由？</t></q><q i="111" t="2015-06-10"><v>19</v><t>零基础如何学习fm2015?</t></q><q i="112" t="2015-04-27"><v>19</v><t>请用图文并茂简单粗暴的办法让一位小白妹子看懂球赛？</t></q><q i="113" t="2015-03-27"><v>19</v><t>足球比赛也增加类似篮球24秒，回场违例等规则会不会让比赛更刺激？</t></q><q i="114" t="2014-02-13"><v>19</v><t>2014年中超有哪些看点？</t></q><q i="115" t="2013-11-08"><v>18</v><t>如果广州恒大输掉2013年亚冠决赛，那会出现怎样的评论呢？</t></q><q i="116" t="2014-01-21"><v>18</v><t>范志毅，郝海东，谁能牛，或者说谁的影响力更大？</t></q><q i="117" t="2013-06-11"><v>18</v><t>C罗在技术层面与一代球王差距在哪里？</t></q><q i="118" t="2014-11-27"><v>18</v><t>如果要世界顶级门将守门，让业余玩球的人去踢点球，10个能进几个？</t></q><q i="119" t="2015-06-06"><v>18</v><t>欧冠决赛 ，巴塞罗那和尤文图斯你更看好谁夺冠？理由？</t></q><q i="120" t="2015-06-03"><v>18</v><t>如果中国队申办世界杯成功，会不会出现大量中国球迷穿外国球衣观看比赛的情况？</t></q><q i="121" t="2015-05-25"><v>18</v><t>世界上最伟大的守门员是谁？</t></q><q i="122" t="2014-03-11"><v>18</v><t>一只球队的教练和核心队员都变了，支持你继续支持它的又是什么?</t></q><q i="123" t="2015-11-02"><v>20</v><t>为什么感觉只有米兰球迷一直在怀念过去？</t></q><q i="124" t="2013-01-10"><v>17</v><t>足球迷们为自己的喜欢的球队相互攻击对骂，这可以说是一种“足球文化”？</t></q><q i="125" t="2015-02-27"><v>17</v><t>从综合水平来说，巴萨和皇马哪一个更优秀？</t></q><q i="126" t="2014-07-17"><v>17</v><t>伪球迷如何晋升为球迷？</t></q><q i="127" t="2014-07-05"><v>17</v><t>巴西下一轮有可能战胜哥伦比亚吗？</t></q><q i="128" t="2015-07-04"><v>17</v><t>怎么伪装成国米球迷?</t></q><q i="129" t="2014-04-12"><v>17</v><t>守门员有何技巧?</t></q><q i="130" t="2016-09-02"><v>17</v><t>蒿俊闵是不是算已经废掉了？</t></q><q i="131" t="2014-02-22"><v>17</v><t>你认为现在的这支切尔西还能不能战胜巴萨？</t></q><q i="132" t="2014-02-19"><v>17</v><t>杰拉德位置后移效果如何？</t></q><q i="133" t="2014-06-20"><v>17</v><t>西班牙队几名首发位置不稳固的中场球员席尔瓦、马塔、卡索拉的风格有什么不同？</t></q><q i="134" t="2013-11-13"><v>16</v><t>中国有意大利的球迷、德国的球迷、甚至日本韩国的球迷，那么存不存在外国的中国球迷？</t></q><q i="135" t="2013-04-10"><v>16</v><t>哪场足球比赛给你留下最深刻的印象？</t></q><q i="136" t="2015-11-19"><v>16</v><t>你给英超俱乐部或球星写信的经历是怎样的？</t></q><q i="137" t="2015-04-13"><v>16</v><t>请用图文并茂简单粗暴的办法让一位小白妹子看懂球赛？</t></q><q i="138" t="2014-06-28"><v>16</v><t>巴西世界杯亚洲球队集体出局是真实水平的反映吗？</t></q><q i="139" t="2014-05-01"><v>16</v><t>梅西能离开巴萨吗？</t></q><q i="140" t="2014-02-17"><v>14</v><t>如何快速接近一個球迷？</t></q><q i="141" t="2016-02-26"><v>15</v><t>你知道的足球史最富有悲情色彩的比赛是哪场？</t></q><q i="142" t="2016-03-13"><v>14</v><t>做河南建业队的球迷是一种什么样的体验？</t></q><q i="143" t="2015-05-31"><v>15</v><t>如果中国队申办世界杯成功，会不会出现大量中国球迷穿外国球衣观看比赛的情况？</t></q><q i="144" t="2015-01-12"><v>15</v><t>怎么评价pptv周亮在解说时公然称江苏舜天球员为苏北狗？</t></q><q i="145" t="2014-07-09"><v>15</v><t>曾经球星辈出的巴西队为何近年来人才凋零、青黄不接？是否是体制原因？</t></q><q i="146" t="2014-03-21"><v>15</v><t>怎样可以拿到切尔西官方球员的签名？</t></q><q i="147" t="2015-01-11"><v>14</v><t>为啥叫西班牙国家德比?</t></q><q i="148" t="2014-12-04"><v>14</v><t>喜欢一支足球队跟追星的区别在哪里？</t></q><q i="149" t="2014-09-03"><v>14</v><t>作为一个德国队伪球迷，看到巴西被战车如此碾压没有特别高兴，反而想哭是为什么？</t></q><q i="150" t="2016-02-02"><v>14</v><t>怎样看待阿根廷队拉维奇向主教练泼水的行为？</t></q><q i="151" t="2013-11-22"><v>13</v><t>如何证明：足球是世界第一运动?</t></q><q i="152" t="2013-05-26"><v>13</v><t>欧洲冠军联赛的冠军登顶领奖时为什么要爬107级台阶，107级台阶有什么象征意义吗？</t></q><q i="153" t="2013-05-23"><v>13</v><t>如何评价申思的职业生涯？</t></q><q i="154" t="2015-02-05"><v>13</v><t>如果你是足球迷，给你一份不错的工作，你会选择在西，英，德，意，法，俄，葡，巴西哪个国家生活？</t></q><q i="155" t="2015-01-03"><v>13</v><t>我就想问问，2014年做一个国际米兰球迷是什么感觉？</t></q><q i="156" t="2015-01-30"><v>13</v><t>你为什么喜欢马竞?</t></q><q i="157" t="2014-06-09"><v>13</v><t>为什么足球明星的女人都是女友而不是老婆？</t></q><q i="158" t="2014-02-24"><v>13</v><t>如何评价「球迷」？</t></q><q i="159" t="2014-02-22"><v>13</v><t>在FM的游戏过程中，你遇见过什么搞笑的情况？</t></q><q i="160" t="2014-10-20"><v>13</v><t>想要看一些专业性的球评，都有哪些网站和博客（最好不用翻墙）？</t></q><q i="161" t="2013-10-30"><v>12</v><t>如何快速接近一個球迷？</t></q><q i="162" t="2013-10-01"><v>12</v><t>恒大等于中国足球吗，中国足球等于恒大呢？</t></q><q i="163" t="2013-07-17"><v>13</v><t>足球迷们，平时都分享些啥？</t></q><q i="164" t="2013-08-26"><v>12</v><t>范志毅，郝海东，谁能牛，或者说谁的影响力更大？</t></q><q i="165" t="2013-07-03"><v>12</v><t>在未来的某一天能否做到民主选取国足主帅？</t></q><q i="166" t="2013-06-10"><v>12</v><t>C罗在技术层面与一代球王差距在哪里？</t></q><q i="167" t="2014-11-18"><v>12</v><t>中国能不能建立起会员制足球俱乐部？</t></q><q i="168" t="2015-08-19"><v>12</v><t>不懂足球规则，在别人看球或者讨论足球时要怎么做？</t></q><q i="169" t="2014-05-03"><v>12</v><t>男朋友是拜仁球迷，输球了怎么安慰他？</t></q><q i="170" t="2014-03-24"><v>12</v><t>球门后的球迷看比赛是什么感受？</t></q><q i="171" t="2014-03-24"><v>12</v><t>女生如何练习足球？</t></q><q i="172" t="2013-09-04"><v>11</v><t>比利时会在巴西世界杯会成为黑马吗？</t></q><q i="173" t="2014-04-06"><v>11</v><t>请客观综合地评价下莫德里奇？</t></q><q i="174" t="2013-05-23"><v>11</v><t>中国足球最好的球市是哪里？</t></q><q i="175" t="2015-03-13"><v>11</v><t>踢球会造成O型腿吗？</t></q><q i="176" t="2014-10-21"><v>11</v><t>给曼联写信，有哪些具体的可操作方法？</t></q><q i="177" t="2014-12-01"><v>11</v><t>德国球迷在德国大领先情况下会希望巴西进球吗？为什么？</t></q><q i="178" t="2014-07-01"><v>11</v><t>巴西前国家足球队队长为什么叫卡福（Cafu）？</t></q><q i="179" t="2016-03-31"><v>11</v><t>蒿俊闵是不是算已经废掉了？</t></q><q i="180" t="2014-02-13"><v>11</v><t>2014年中超有哪些看点？</t></q><q i="181" t="2014-10-21"><v>11</v><t>想要看一些专业性的球评，都有哪些网站和博客（最好不用翻墙）？</t></q><q i="182" t="2013-05-24"><v>10</v><t>中国足球最好的球市是哪里？</t></q><q i="183" t="2013-04-15"><v>10</v><t>高水平足球比赛中，高水平球员是怎样发角球的？</t></q><q i="184" t="2013-04-10"><v>10</v><t>哪场足球比赛给你留下最深刻的印象？</t></q><q i="185" t="2014-01-21"><v>10</v><t>是不是喜欢罗纳尔多就特别有优越感？喜欢梅西就是小孩儿？</t></q><q i="186" t="2014-10-04"><v>11</v><t>怎么评价pptv周亮在解说时公然称江苏舜天球员为苏北狗？</t></q><q i="187" t="2014-08-29"><v>10</v><t>赫斯基不会进球的梗是怎么来的？既然不能进球为什么能在英格兰国家队和联赛混这么多年？</t></q><q i="188" t="2014-07-15"><v>10</v><t>2018年俄罗斯世界杯上可能会发生什么？</t></q><q i="189" t="2014-06-28"><v>10</v><t>怎样看待阿根廷队拉维奇向主教练泼水的行为？</t></q><q i="190" t="2014-06-12"><v>10</v><t>如何让不爱足球的女朋友或老婆不打扰自己看世界杯？或者能让她欢天喜地的陪着一起看。</t></q><q i="191" t="2014-03-25"><v>11</v><t>女生如何练习足球？</t></q><q i="192" t="2014-03-02"><v>10</v><t>9人制足球如何安排战术？</t></q><q i="193" t="2014-02-16"><v>10</v><t>为什么足球运动员喜欢在被打到其他部位时捂着脸倒地？</t></q><q i="194" t="2014-01-27"><v>13</v><t>送什么礼物给喜欢足球的女生呢？</t></q><q i="195" t="2015-11-06"><v>11</v><t>英国的贵族绅士风范能部分解释英超赛场球员的友好吗？</t></q><q i="196" t="2013-09-03"><v>9</v><t>如何理解“欧冠经验”？与联赛的经验有何区别？有何具体的表现呢？</t></q><q i="197" t="2015-08-23"><v>9</v><t>朋友很喜欢阿圭罗 她过生日该送什么关于阿圭罗的礼物好.？</t></q><q i="198" t="2015-07-15"><v>9</v><t>怎样清洗门将手套？</t></q><q i="199" t="2014-08-26"><v>9</v><t>就两个人怎么愉快地踢球？</t></q><q i="200" t="2014-08-03"><v>11</v><t>为了国家荣誉，可以把所有国家队球员放进一个俱乐部吗？</t></q><q i="201" t="2015-06-23"><v>9</v><t>你喜欢因扎吉的什么？</t></q><q i="202" t="2014-06-17"><v>9</v><t>为什么像佩佩这样的球品还能继续踢球？</t></q><q i="203" t="2014-04-01"><v>9</v><t>有哪些优质的足球球迷类微信公众号？</t></q><q i="204" t="2014-02-17"><v>9</v><t>欧战经验只是当成个参数说说而已？还是确有其事？</t></q><q i="205" t="2014-01-15"><v>9</v><t>为什么足球射门很容易打中门框？</t></q><q i="206" t="2013-12-31"><v>9</v><t>近年电影和足球为什么那么火？对应的是否从业者需求也会增加？</t></q><q i="207" t="2013-11-18"><v>9</v><t>有没有足球女教练？</t></q><q i="208" t="2013-10-17"><v>8</v><t>为何中国足球国家队选择了白色队服？</t></q><q i="209" t="2016-02-26"><v>8</v><t>你知道的足球史最富有悲情色彩的比赛是哪场？</t></q><q i="210" t="2013-09-03"><v>8</v><t>比利时会在巴西世界杯会成为黑马吗？</t></q><q i="211" t="2016-01-26"><v>8</v><t>自己主队有一个世界级门将是什么体验？</t></q><q i="212" t="2013-07-08"><v>8</v><t>天赋高的球员大多是进攻型，这个说法有道理吗？</t></q><q i="213" t="2013-02-07"><v>8</v><t>你给英超俱乐部或球星写信的经历是怎样的？</t></q><q i="214" t="2016-05-02"><v>8</v><t>做河南建业队的球迷是一种什么样的体验？</t></q><q i="215" t="2015-01-15"><v>8</v><t>作为多特蒙德球迷是一种怎样的体验？</t></q><q i="216" t="2014-09-11"><v>11</v><t>为什么很多人都说高估了鲁尼的能力？真的是这样吗？</t></q><q i="217" t="2014-07-14"><v>8</v><t>因为自己喜爱的球队未能夺冠而痛哭流涕甚至伤心难过一整天，值吗？为什么？</t></q><q i="218" t="2014-07-11"><v>8</v><t>如何评价罗本在本次世界杯中的表现。?</t></q><q i="219" t="2014-07-10"><v>8</v><t>如何评价阿根廷队？</t></q><q i="220" t="2014-06-15"><v>8</v><t>足球比赛中有哪些很无语的规则？</t></q><q i="221" t="2014-06-12"><v>8</v><t>如何让不爱足球的女朋友或老婆不打扰自己看世界杯？或者能让她欢天喜地的陪着一起看。</t></q><q i="222" t="2016-03-21"><v>8</v><t>守门员有何技巧?</t></q><q i="223" t="2015-04-16"><v>9</v><t>如何评价多特蒙德的罗伊斯？</t></q><q i="224" t="2014-07-03"><v>8</v><t>赌球应该具备哪些资源？</t></q><q i="225" t="2014-01-13"><v>9</v><t>这是哪个球队？</t></q><q i="226" t="2013-11-12"><v>7</v><t>中国有意大利的球迷、德国的球迷、甚至日本韩国的球迷，那么存不存在外国的中国球迷？</t></q><q i="227" t="2013-10-02"><v>7</v><t>是什么原因支持着保级水平球队的球迷依然坚守？</t></q><q i="228" t="2013-09-08"><v>7</v><t>给曼联俱乐部写信求签名，英文信件怎么写？</t></q><q i="229" t="2015-12-11"><v>7</v><t>自己主队有一个世界级门将是什么体验？</t></q><q i="230" t="2013-07-26"><v>7</v><t>梅西拿了这么多年的足球先生，是因为他确实伟大，还是因为这是足坛低迷的表现?</t></q><q i="231" t="2013-04-11"><v>7</v><t>在学校踢院级的足球赛不自信怎么办？</t></q><q i="232" t="2015-09-15"><v>7</v><t>我女朋友迷恋足球，但我很不支持，她问我说：如果你是回民我逼着你吃猪肉你吃吗？我该怎么回？</t></q><q i="233" t="2015-04-16"><v>7</v><t>足球比赛中倒挂金钩的技术意义是什么？</t></q><q i="234" t="2015-01-11"><v>7</v><t>作为多特蒙德球迷是一种怎样的体验？</t></q><q i="235" t="2014-10-23"><v>7</v><t>中国是从什么时候开始有曼城球迷的？</t></q><q i="236" t="2014-09-12"><v>7</v><t>哪位足球运动员靠演技度过足球生涯，从未踢过球，每次都装病不上场？</t></q><q i="237" t="2014-08-03"><v>7</v><t>为什么职业足球球员不能进行潜水，登山，骑行？</t></q><q i="238" t="2014-08-03"><v>8</v><t>为什么职业足球球员不能进行潜水，登山，骑行？</t></q><q i="239" t="2014-07-02"><v>7</v><t>巴西前国家足球队队长为什么叫卡福（Cafu）？</t></q><q i="240" t="2014-06-30"><v>8</v><t>如何评价智利国家队？</t></q><q i="241" t="2014-06-19"><v>7</v><t>如何最快速判断一个人是真球迷还是伪球迷？</t></q><q i="242" t="2014-04-30"><v>9</v><t>男朋友是拜仁球迷，输球了怎么安慰他？</t></q><q i="243" t="2014-04-20"><v>7</v><t>为什么沃尔科特不像贝尔一样强行超车？</t></q><q i="244" t="2015-02-06"><v>7</v><t>如何评价多特蒙德的罗伊斯？</t></q><q i="245" t="2014-03-30"><v>7</v><t>有哪些经典的雨中/雪中足球比赛？</t></q><q i="246" t="2014-03-27"><v>7</v><t>蒿俊闵是不是算已经废掉了？</t></q><q i="247" t="2013-11-28"><v>7</v><t>如果您的孩子告诉您他的梦想是踢足球，您会支持吗？</t></q><q i="248" t="2013-09-22"><v>6</v><t>为什么足球门将接回传球时，必须先脚触下，才能用手接？</t></q><q i="249" t="2015-04-11"><v>6</v><t>一个人如何进行系统的足球训练?</t></q><q i="250" t="2015-03-27"><v>6</v><t>足球比赛也增加类似篮球24秒，回场违例等规则会不会让比赛更刺激？</t></q><q i="251" t="2015-03-12"><v>6</v><t>有个爱足球、不是对手球队球迷的男朋友是种什么体验？</t></q><q i="252" t="2015-01-20"><v>6</v><t>足球里评价球迷“风险狗”是什么意思？</t></q><q i="253" t="2014-11-06"><v>6</v><t>中国是从什么时候开始有曼城球迷的？</t></q><q i="254" t="2014-07-17"><v>6</v><t>球员假摔为何仍十分盛行？</t></q><q i="255" t="2014-07-16"><v>6</v><t>华金和雷耶斯为什么都没有取得预期那么高的成就？</t></q><q i="256" t="2014-04-22"><v>6</v><t>完全不懂足球如何在 2014 年世界杯期间装作懂球？</t></q><q i="257" t="2014-04-14"><v>7</v><t>定位球防守是怎么布置的？</t></q></SubTopic>